cosa/__init__.py
cosa/cosa.py
cosa/transform.py
cosa/utils.py
cosabot-0.0.9.dist-info/LICENSE
cosabot-0.0.9.dist-info/METADATA
cosabot-0.0.9.dist-info/WHEEL
cosabot-0.0.9.dist-info/top_level.txt
cosabot-0.0.9.dist-info/RECORD
