Metadata-Version: 2.1
Name: cosabot
Version: 0.0.9
Summary: Computer Optic Semantics
Home-page: UNKNOWN
Author: Alfredo Lozano
Author-email: lozanoa94@gmail.com
License: UNKNOWN
Platform: UNKNOWN
License-File: LICENSE
Requires-Dist: scipy
Requires-Dist: scikit-image
Requires-Dist: scikit-learn
Requires-Dist: numpy
